transformHealthEventHubModels/DataStandardisationTrigger.py
transformHealthEventHubModels/__init__.py
transformHealthEventHubModels/insertOne.py
transformHealthEventHubModels/updateOne.py
transformHealthEventHubModels/utils.py
th_eventhub_models-0.0.3.dist-info/LICENSE
th_eventhub_models-0.0.3.dist-info/METADATA
th_eventhub_models-0.0.3.dist-info/WHEEL
th_eventhub_models-0.0.3.dist-info/top_level.txt
th_eventhub_models-0.0.3.dist-info/RECORD
